power_bi_api/__init__.py
power_bi_api/helpers/auth.py
power_bi_api/helpers/https_base.py
power_bi_api/models/activity/controller.py
power_bi_api/models/activity/service.py
power_bi_api/models/activity/urls.py
power_bi_api/models/app/controller.py
power_bi_api/models/app/service.py
power_bi_api/models/app/urls.py
power_bi_api/models/capacity/controller.py
power_bi_api/models/capacity/service.py
power_bi_api/models/capacity/urls.py
power_bi_api/models/dashboard/controller.py
power_bi_api/models/dashboard/service.py
power_bi_api/models/dashboard/urls.py
power_bi_api/models/dataflow/controller.py
power_bi_api/models/dataflow/service.py
power_bi_api/models/dataflow/urls.py
power_bi_api/models/dataset/controller.py
power_bi_api/models/dataset/service.py
power_bi_api/models/dataset/urls.py
power_bi_api/models/group/controller.py
power_bi_api/models/group/service.py
power_bi_api/models/group/urls.py
power_bi_api/models/pbi_import/controller.py
power_bi_api/models/pbi_import/service.py
power_bi_api/models/pbi_import/urls.py
power_bi_api/models/pipeline/controller.py
power_bi_api/models/pipeline/service.py
power_bi_api/models/pipeline/urls.py
power_bi_api/models/profile/controller.py
power_bi_api/models/profile/service.py
power_bi_api/models/profile/urls.py
power_bi_api/models/report/controller.py
power_bi_api/models/report/service.py
power_bi_api/models/report/urls.py
power_bi_api/models/user/controller.py
power_bi_api/models/user/service.py
power_bi_api/models/user/urls.py
power_bi_api/models/workspace/controller.py
power_bi_api/models/workspace/service.py
power_bi_api/models/workspace/urls.py
power_bi_api_admin-0.1.5.dist-info/LICENSE
power_bi_api_admin-0.1.5.dist-info/METADATA
power_bi_api_admin-0.1.5.dist-info/WHEEL
power_bi_api_admin-0.1.5.dist-info/RECORD
