Metadata-Version: 2.1
Name: power-bi-api-admin
Version: 0.1.5
Summary: Power BI API Admin to extract data of use metricts!
License: MIT
Author: stone_people_analytics
Author-email: systems-techpeople@stone.com.br
Maintainer: diogo56
Maintainer-email: diogo.amorim2001@gmail.com
Requires-Python: >=3.9,<4.0
Classifier: License :: OSI Approved :: MIT License
Classifier: Programming Language :: Python :: 3
Classifier: Programming Language :: Python :: 3.9
Classifier: Programming Language :: Python :: 3.10
Classifier: Programming Language :: Python :: 3.11
Classifier: Programming Language :: Python :: 3.12
Requires-Dist: adal (>=1.2.7,<2.0.0)
Requires-Dist: aiohttp (>=3.9.5,<4.0.0)
Requires-Dist: python-decouple (>=3.8,<4.0)
